slurmflow/__init__.py
slurmflow/dag.py
slurmflow/job.py
slurmflow-0.2.2.dist-info/LICENSE
slurmflow-0.2.2.dist-info/METADATA
slurmflow-0.2.2.dist-info/WHEEL
slurmflow-0.2.2.dist-info/top_level.txt
slurmflow-0.2.2.dist-info/RECORD
