Metadata-Version: 2.1
Name: slurmflow
Version: 0.2.2
Summary: DAG interface for SLURM schedulers
Home-page: https://github.com/ianwesleyarmstrong/slurmflow
Author: Ian Armstrong
Author-email: ianwesleyarmstrong@gmail.com
License: UNKNOWN
Project-URL: Bug Tracker, https://github.com/ianwesleyarmstrong/slurmflow/isues
Platform: UNKNOWN
Classifier: Programming Language :: Python :: 3
Classifier: License :: OSI Approved :: MIT License
Classifier: Operating System :: OS Independent
Requires-Python: >=3.7
License-File: LICENSE
Requires-Dist: numpy
Requires-Dist: networkx (==2.6.2)
Requires-Dist: matplotlib
